flaskexample/__init__.py
flaskexample/auth/__init__.py
flaskexample/auth/models.py
flaskexample/auth/views.py
flaskexample/blog/__init__.py
flaskexample/blog/models.py
flaskexample/blog/views.py
flaskexample/config.py
flaskexample/db.py
flaskexample/schema.sql
flaskexample/static/style.css
flaskexample/templates/404.html
flaskexample/templates/500.html
flaskexample/templates/auth/login.html
flaskexample/templates/auth/register.html
flaskexample/templates/base.html
flaskexample/templates/blog/create.html
flaskexample/templates/blog/index.html
flaskexample/templates/blog/update.html
flaskexample/wsgi.py
flaskexample-0.1.1.dist-info/LICENSE
flaskexample-0.1.1.dist-info/METADATA
flaskexample-0.1.1.dist-info/WHEEL
flaskexample-0.1.1.dist-info/RECORD
