Metadata-Version: 2.1
Name: flaskexample
Version: 0.1.1
Summary: This is a Python demo project with Flask
Author: Yakir
Author-email: yakir3@duck.com
Requires-Python: >=3.12,<4.0
Classifier: Programming Language :: Python :: 3
Classifier: Programming Language :: Python :: 3.12
Requires-Dist: coverage (>=7.6.1,<8.0.0)
Requires-Dist: flask (>=3.0.3,<4.0.0)
Requires-Dist: pytest (>=8.3.3,<9.0.0)
Requires-Dist: uwsgi (>=2.0.26,<3.0.0)
